epaaws/__init__.py
epaaws/mp2022.py
epaaws/util.py
epaaws/tests/__init__.py
epaaws/tests/test_main.py
epaaws-1.0.0.dist-info/LICENSE
epaaws-1.0.0.dist-info/METADATA
epaaws-1.0.0.dist-info/WHEEL
epaaws-1.0.0.dist-info/top_level.txt
epaaws-1.0.0.dist-info/RECORD
