Metadata-Version: 2.1
Name: epaaws
Version: 1.0.0
Summary: Library to facilitate analysis of EPA's data on Amazon's Registry of Open Data.
Author: Barron H. Henderson
Author-email: barronh@gmail.com
License: GNU GENERAL PUBLIC LICENSE
Classifier: Development Status :: 3 - Alpha
Classifier: Intended Audience :: Science/Research
Classifier: Intended Audience :: Education
Classifier: License :: OSI Approved :: GNU General Public License v3 or later (GPLv3+)
Classifier: Programming Language :: Python
Classifier: Programming Language :: Python :: 3
Classifier: Programming Language :: Python :: 3.9
Classifier: Programming Language :: Python :: 3.10
Classifier: Programming Language :: Python :: 3.11
Classifier: Programming Language :: Python :: 3.12
Classifier: Topic :: Scientific/Engineering :: Visualization
Requires-Python: >=3.9
License-File: LICENSE
Requires-Dist: boto3 >=1.30.0
Requires-Dist: botocore >=1.30.0
Requires-Dist: xarray >=2023.12.0
Requires-Dist: pandas >=2.0.0
Requires-Dist: numpy >=1.20.0
Requires-Dist: scipy >=1.7.0
Requires-Dist: cmaqsatproc >=0.3.1
Requires-Dist: pycno >=0.3.0
Requires-Dist: matplotlib >=3.0.0
